neuroimaging/__init__.py
neuroimaging/inference.py
neuroimaging/model_loader.py
neuroimaging-1.0.0.dist-info/licenses/LICENSE
neuroimaging_models/__init__.py
neuroimaging_models/unet3d.py
neuroimaging-1.0.0.dist-info/METADATA
neuroimaging-1.0.0.dist-info/WHEEL
neuroimaging-1.0.0.dist-info/top_level.txt
neuroimaging-1.0.0.dist-info/RECORD
