Metadata-Version: 2.4
Name: neuroimaging
Version: 1.0.0
Summary: 3D brain MRI segmentation with a packaged UNet3D trained model and simple inference API.
Requires-Python: >=3.10
License-File: LICENSE
Requires-Dist: monai>=1.4.0
Requires-Dist: nibabel>=5.3.2
Requires-Dist: numpy>=1.26.4
Requires-Dist: torch>=2.9.0
Requires-Dist: torchsummary>=1.5.1
Requires-Dist: tqdm>=4.67.1
Requires-Dist: matplotlib>=3.8.0
Requires-Dist: scikit-image>=0.25.2
Requires-Dist: build>=1.3.0
Dynamic: license-file
